{"createdAt":"2025-09-16T14:46:46.697Z","updatedAt":"2025-09-16T15:03:43.000Z","id":"gduZnmrzOULw4MJc","name":"back-up n8n workflows","active":true,"isArchived":false,"nodes":[{"parameters":{},"id":"617ba227-8cbc-400d-a198-b5b174ae9b53","name":"Execute workflow","type":"n8n-nodes-base.manualTrigger","typeVersion":1,"position":[-1024,128]},{"parameters":{"options":{}},"id":"9333aa95-bbb2-48c4-8898-28d49a7845d9","name":"Set date","type":"n8n-nodes-base.dateTime","typeVersion":2,"position":[-816,128]},{"parameters":{"operation":"formatDate","date":"={{ $json.currentDate }}","format":"custom","customFormat":"dd-MM-yyyy/H:mm","options":{}},"id":"2bba2c95-bb0c-42c9-badc-1b9bf5a8b401","name":"Format date","type":"n8n-nodes-base.dateTime","typeVersion":2,"position":[-608,128]},{"parameters":{"keepOnlySet":true,"values":{"string":[{"name":"commitDate","value":"={{ $json.formattedDate }}"}]},"options":{}},"id":"167f57e3-0baa-4ab1-808d-ff02e8cf7c97","name":"Set commit date","type":"n8n-nodes-base.set","typeVersion":2,"position":[-416,128]},{"parameters":{"authentication":"oAuth2","resource":"file","operation":"list","owner":{"__rl":true,"value":"martial888307","mode":"name"},"repository":{"__rl":true,"value":"backup-n8n-vps2","mode":"list","cachedResultName":"backup-n8n-vps2","cachedResultUrl":"https://github.com/martial888307/backup-n8n-vps2"}},"id":"ae9d6482-8154-4638-88c1-c9a9856f5492","name":"List files from repository [GITHUB]","type":"n8n-nodes-base.github","typeVersion":1,"position":[-208,128],"alwaysOutputData":true,"webhookId":"11c67b4d-dd77-441c-a3e4-77102b6a0466","credentials":{"githubOAuth2Api":{"id":"tPaGWDwb9ZiAjWYH","name":"GitHub account"}}},{"parameters":{"operation":"aggregateItems","fieldsToAggregate":{"fieldToAggregate":[{"fieldToAggregate":"name"}]},"options":{}},"id":"f3d8db02-1f23-4021-9e5e-5d4347d30153","name":"Combine file names [GITHUB]","type":"n8n-nodes-base.itemLists","typeVersion":2.1,"position":[-16,128]},{"parameters":{"filters":{},"requestOptions":{}},"id":"46fd6970-f3a3-429c-b87a-fe91ff868362","name":"Retrieve workflows [N8N]","type":"n8n-nodes-base.n8n","typeVersion":1,"position":[192,128],"credentials":{"n8nApi":{"id":"Ff2cE2sK4e8t6oH1","name":"n8n account"}}},{"parameters":{"mode":"jsonToBinary","options":{"fileName":"={{ $json.name.replace(/\\s+/g, '-').toLowerCase() }}-{{ $json.id }}.json"}},"id":"61ce4a08-5724-4256-a766-a4f6fc1b7b6f","name":"Move JSON to binary","type":"n8n-nodes-base.moveBinaryData","typeVersion":1,"position":[384,128]},{"parameters":{"batchSize":1,"options":{}},"id":"83236b09-0a50-4772-b081-739afb7fc5b8","name":"Split to single items","type":"n8n-nodes-base.splitInBatches","typeVersion":2,"position":[624,128]},{"parameters":{"conditions":{"string":[{"value1":"={{ $node['Combine file names [GITHUB]'].json.name }}","operation":"contains","value2":"={{ $binary.data.fileName }}"}]}},"id":"eceddef6-b20a-4d96-b267-88abfa914958","name":"Check if file exists in repository","type":"n8n-nodes-base.if","typeVersion":1,"position":[864,48]},{"parameters":{"authentication":"oAuth2","resource":"file","operation":"edit","owner":{"__rl":true,"value":"martial888307","mode":"name"},"repository":{"__rl":true,"value":"backup-n8n-vps2","mode":"list","cachedResultName":"backup-n8n-vps2","cachedResultUrl":"https://github.com/martial888307/backup-n8n-vps2"},"filePath":"={{ $binary.data.fileName }}","binaryData":true,"commitMessage":"=backup-{{ $node['Set commit date'].json.commitDate }}"},"id":"81c8997f-59e2-4b1a-8abf-241fc281656f","name":"Update file [GITHUB]","type":"n8n-nodes-base.github","typeVersion":1,"position":[1088,-160],"webhookId":"5b596d8e-abdd-4adc-8ed5-d695280f7a33","credentials":{"githubOAuth2Api":{"id":"tPaGWDwb9ZiAjWYH","name":"GitHub account"}}},{"parameters":{"authentication":"oAuth2","resource":"file","owner":{"__rl":true,"value":"martial888307","mode":"name"},"repository":{"__rl":true,"value":"backup-n8n-vps2","mode":"list","cachedResultName":"backup-n8n-vps2","cachedResultUrl":"https://github.com/martial888307/backup-n8n-vps2"},"filePath":"={{ $binary.data.fileName }}","binaryData":true,"commitMessage":"=backup-{{ $node['Set commit date'].json.commitDate }}"},"id":"0b9a8465-0d01-4676-abaa-6c6c113ec09c","name":"Upload file [GITHUB]","type":"n8n-nodes-base.github","typeVersion":1,"position":[1088,240],"webhookId":"9d9553e0-997b-4c30-9aca-8a7be9213dc1","credentials":{"githubOAuth2Api":{"id":"tPaGWDwb9ZiAjWYH","name":"GitHub account"}}},{"parameters":{"content":"## Trigger\nYou can change it to [\"Schedule\" trigger](https://docs.n8n.io/integrations/builtin/core-nodes/n8n-nodes-base.scheduletrigger/) to make backups on regular basis.","height":339.51767272727324,"width":182.4715262478496},"id":"903059b9-be5e-4d64-95b1-c8d788daa60a","name":"Sticky Note","type":"n8n-nodes-base.stickyNote","typeVersion":1,"position":[-1056,-32]},{"parameters":{"content":"## Set and format date/time\nThose nodes are responsible for setting a current date and time in format `dd-MM-yyyy/H:mm`. Date and time are used to compose commit messages in GitHub, for example: `backup-12-07-2023/14:18`.","height":339.42690909090965,"width":585.4045090909088},"id":"8dd9dd7f-a62e-4a6d-9553-1e9f1988711b","name":"Sticky Note1","type":"n8n-nodes-base.stickyNote","typeVersion":1,"position":[-864,-32]},{"parameters":{"content":"## Make a list of existing files\nReturn a list of existing files (backups) in GitHub repository. Data returned by those nodes is used by \"IF\" node (later in workflow) to check whether the backup files should be created or updated.","height":339.42690909090965,"width":389.89265454545443},"id":"74b26433-f91f-418f-baa9-83e63f2e3bab","name":"Sticky Note2","type":"n8n-nodes-base.stickyNote","typeVersion":1,"position":[-256,-32]},{"parameters":{"content":"## Retrieve workflows\nGet all workflows form your n8n instance. Remember that **your credentials need to point to the instance that you want to backup.**","height":339.42690909090965,"width":384.14708363636373},"id":"875b2ad5-c429-4215-bb88-a38699f651c2","name":"Sticky Note3","type":"n8n-nodes-base.stickyNote","typeVersion":1,"position":[176,-32]},{"parameters":{"content":"## Upload backup\nSplit JSON files into batches of 1, check if they were uploaded to repository before. If yes (true), upload the new version of the file. Otherwise (false) create the file in repository.","height":731.633426614796,"width":703.8733020263451},"id":"82a7644a-b7e0-403a-8909-3af5be104f92","name":"Sticky Note4","type":"n8n-nodes-base.stickyNote","typeVersion":1,"position":[576,-304]},{"parameters":{"content":"## ⚠️ Note\n\n1. Complete video guide for this workflow is available [on my YouTube](https://www.youtube.com/watch?v=dNuVuoPD0Jo). \n2. Remember to add your credentials and configure GitHub nodes (covered in the video guide).\n3. If you like this workflow, please subscribe to [my YouTube channel](https://www.youtube.com/@workfloows) and/or [my newsletter](https://workfloows.com/).\n\n**Thank you for your support!**","height":234.82946582693546,"width":508.8662091091177},"id":"42805429-937a-4cc6-a7a8-27c1d992a62d","name":"Sticky Note5","type":"n8n-nodes-base.stickyNote","typeVersion":1,"position":[-1056,-304]},{"parameters":{"rule":{"interval":[{}]}},"type":"n8n-nodes-base.scheduleTrigger","typeVersion":1.2,"position":[-992,384],"id":"36e1268b-2161-4809-a675-2eb3119ae4a2","name":"Schedule Trigger"}],"connections":{"Execute workflow":{"main":[[{"node":"Set date","type":"main","index":0}]]},"Set date":{"main":[[{"node":"Format date","type":"main","index":0}]]},"Format date":{"main":[[{"node":"Set commit date","type":"main","index":0}]]},"Set commit date":{"main":[[{"node":"List files from repository [GITHUB]","type":"main","index":0}]]},"List files from repository [GITHUB]":{"main":[[{"node":"Combine file names [GITHUB]","type":"main","index":0}]]},"Combine file names [GITHUB]":{"main":[[{"node":"Retrieve workflows [N8N]","type":"main","index":0}]]},"Retrieve workflows [N8N]":{"main":[[{"node":"Move JSON to binary","type":"main","index":0}]]},"Move JSON to binary":{"main":[[{"node":"Split to single items","type":"main","index":0}]]},"Split to single items":{"main":[[{"node":"Check if file exists in repository","type":"main","index":0}]]},"Check if file exists in repository":{"main":[[{"node":"Update file [GITHUB]","type":"main","index":0}],[{"node":"Upload file [GITHUB]","type":"main","index":0}]]},"Update file [GITHUB]":{"main":[[{"node":"Split to single items","type":"main","index":0}]]},"Upload file [GITHUB]":{"main":[[{"node":"Split to single items","type":"main","index":0}]]},"Schedule Trigger":{"main":[[{"node":"Set date","type":"main","index":0}]]}},"settings":{"executionOrder":"v1","callerPolicy":"workflowsFromSameOwner","errorWorkflow":"4xKLB9RPfrowY9h4"},"staticData":{"node:Schedule Trigger":{"recurrenceRules":[]}},"meta":{"templateCredsSetupCompleted":true},"pinData":{},"versionId":"634cbd4e-51a0-4cf8-bb05-22aba410060e","triggerCount":1,"shared":[{"createdAt":"2025-09-16T14:46:46.701Z","updatedAt":"2025-09-16T14:46:46.701Z","role":"workflow:owner","workflowId":"gduZnmrzOULw4MJc","projectId":"3csiRTB7Dv0MNPzt"}],"tags":[]}